pbar_parallel.py
pbar_parallel-0.0.3.dist-info/LICENSE.txt
pbar_parallel-0.0.3.dist-info/METADATA
pbar_parallel-0.0.3.dist-info/WHEEL
pbar_parallel-0.0.3.dist-info/top_level.txt
pbar_parallel-0.0.3.dist-info/RECORD
